ambiexa/__init__.py
ambiexa/ambiexa__init__.py
ambiexa-0.0.2.dist-info/METADATA
ambiexa-0.0.2.dist-info/WHEEL
ambiexa-0.0.2.dist-info/top_level.txt
ambiexa-0.0.2.dist-info/RECORD
