Metadata-Version: 2.4
Name: ambiexa
Version: 0.0.2
Summary: Ambiexa – Official namespace reservation
Author-email: AMB IEXA <info@auraverde.eco>
License: Proprietary
Classifier: Development Status :: 1 - Planning
Classifier: Intended Audience :: Developers
Classifier: License :: Other/Proprietary License
Classifier: Programming Language :: Python :: 3
Requires-Python: >=3.8
